ALU.v
module ALU(
  input         clock,
  input         reset,
  input  [31:0] io_A,
  input  [31:0] io_B,
  input  [1:0]  io_alu_op,
  output [31:0] io_out
);
  wire [31:0] _io_out_T_1 = io_A + io_B; // @[ALU.scala 24:26]
  wire [31:0] _io_out_T_3 = io_A - io_B; // @[ALU.scala 25:26]
  wire [63:0] _io_out_T_4 = io_A * io_B; // @[ALU.scala 26:26]
  wire [31:0] _io_out_T_6 = 2'h0 == io_alu_op ? _io_out_T_1 : 32'h0; // @[Mux.scala 80:57]
  wire [31:0] _io_out_T_8 = 2'h1 == io_alu_op ? _io_out_T_3 : _io_out_T_6; // @[Mux.scala 80:57]
  wire [63:0] _io_out_T_10 = 2'h2 == io_alu_op ? _io_out_T_4 : {{32'd0}, _io_out_T_8}; // @[Mux.scala 80:57]
  assign io_out = _io_out_T_10[31:0]; // @[ALU.scala 23:12]
endmodule

VALU.vcd
$version Generated by VerilatedVcd $end
$date Sun Nov 21 11:22:43 2021
 $end
$timescale   1ns $end

 $scope module TOP $end
  $var wire  1 # clock $end
  $var wire 32 3 io_A [31:0] $end
  $var wire 32 ; io_B [31:0] $end
  $var wire  2 C io_alu_op [1:0] $end
  $var wire 32 K io_out [31:0] $end
  $var wire  1 + reset $end
  $scope module ALU $end
   $var wire  1 # clock $end
   $var wire 32 3 io_A [31:0] $end
   $var wire 32 ; io_B [31:0] $end
   $var wire  2 C io_alu_op [1:0] $end
   $var wire 32 K io_out [31:0] $end
   $var wire  1 + reset $end
  $upscope $end
 $upscope $end
$enddefinitions $end


#0
0#
0+
b00000000000000000000000000000000 3
b00000000000000000000000000000000 ;
b00 C
b00000000000000000000000000000000 K
#1
b01 C
#2
b10 C
#3
b11 C
#4
b00000000000000000000000000000001 ;
b00 C
b00000000000000000000000000000001 K
#5
b01 C
b11111111111111111111111111111111 K
#6
b10 C
b00000000000000000000000000000000 K
#7
b11 C
#8
b00000000000000000000000000000010 ;
b00 C
b00000000000000000000000000000010 K
#9
b01 C
b11111111111111111111111111111110 K
#10
b10 C
b00000000000000000000000000000000 K
#11
b11 C
#12
b00000000000000000000000000000011 ;
b00 C
b00000000000000000000000000000011 K
#13
b01 C
b11111111111111111111111111111101 K
#14
b10 C
b00000000000000000000000000000000 K
#15
b11 C
#16
b00000000000000000000000000000100 ;
b00 C
b00000000000000000000000000000100 K
#17
b01 C
b11111111111111111111111111111100 K
#18
b10 C
b00000000000000000000000000000000 K
#19
b11 C
#20
b00000000000000000000000000000101 ;
b00 C
b00000000000000000000000000000101 K
#21
b01 C
b11111111111111111111111111111011 K
#22
b10 C
b00000000000000000000000000000000 K
#23
b11 C
#24
b00000000000000000000000000000110 ;
b00 C
b00000000000000000000000000000110 K
#25
b01 C
b11111111111111111111111111111010 K
#26
b10 C
b00000000000000000000000000000000 K
#27
b11 C
#28
b00000000000000000000000000000111 ;
b00 C
b00000000000000000000000000000111 K
#29
b01 C
b11111111111111111111111111111001 K
#30
b10 C
b00000000000000000000000000000000 K
#31
b11 C
#32
b00000000000000000000000000001000 ;
b00 C
b00000000000000000000000000001000 K
#33
b01 C
b11111111111111111111111111111000 K
#34
b10 C
b00000000000000000000000000000000 K
#35
b11 C
#36
b00000000000000000000000000001001 ;
b00 C
b00000000000000000000000000001001 K
#37
b01 C
b11111111111111111111111111110111 K
#38
b10 C
b00000000000000000000000000000000 K
#39
b11 C
#40
b00000000000000000000000000001010 ;
b00 C
b00000000000000000000000000001010 K
#41
b01 C
b11111111111111111111111111110110 K
#42
b10 C
b00000000000000000000000000000000 K
#43
b11 C
#44
b00000000000000000000000000000001 3
b00000000000000000000000000000000 ;
b00 C
b00000000000000000000000000000001 K
#45
b01 C
#46
b10 C
b00000000000000000000000000000000 K
#47
b11 C
#48
b00000000000000000000000000000001 ;
b00 C
b00000000000000000000000000000010 K
#49
b01 C
b00000000000000000000000000000000 K
#50
b10 C
b00000000000000000000000000000001 K
#51
b11 C
b00000000000000000000000000000000 K
#52
b00000000000000000000000000000010 ;
b00 C
b00000000000000000000000000000011 K
#53
b01 C
b11111111111111111111111111111111 K
#54
b10 C
b00000000000000000000000000000010 K
#55
b11 C
b00000000000000000000000000000000 K
#56
b00000000000000000000000000000011 ;
b00 C
b00000000000000000000000000000100 K
#57
b01 C
b11111111111111111111111111111110 K
#58
b10 C
b00000000000000000000000000000011 K
#59
b11 C
b00000000000000000000000000000000 K
#60
b00000000000000000000000000000100 ;
b00 C
b00000000000000000000000000000101 K
#61
b01 C
b11111111111111111111111111111101 K
#62
b10 C
b00000000000000000000000000000100 K
#63
b11 C
b00000000000000000000000000000000 K
#64
b00000000000000000000000000000101 ;
b00 C
b00000000000000000000000000000110 K
#65
b01 C
b11111111111111111111111111111100 K
#66
b10 C
b00000000000000000000000000000101 K
#67
b11 C
b00000000000000000000000000000000 K
#68
b00000000000000000000000000000110 ;
b00 C
b00000000000000000000000000000111 K
#69
b01 C
b11111111111111111111111111111011 K
#70
b10 C
b00000000000000000000000000000110 K
#71
b11 C
b00000000000000000000000000000000 K
#72
b00000000000000000000000000000111 ;
b00 C
b00000000000000000000000000001000 K
#73
b01 C
b11111111111111111111111111111010 K
#74
b10 C
b00000000000000000000000000000111 K
#75
b11 C
b00000000000000000000000000000000 K
#76
b00000000000000000000000000001000 ;
b00 C
b00000000000000000000000000001001 K
#77
b01 C
b11111111111111111111111111111001 K
#78
b10 C
b00000000000000000000000000001000 K
#79
b11 C
b00000000000000000000000000000000 K
#80
b00000000000000000000000000001001 ;
b00 C
b00000000000000000000000000001010 K
#81
b01 C
b11111111111111111111111111111000 K
#82
b10 C
b00000000000000000000000000001001 K
#83
b11 C
b00000000000000000000000000000000 K
#84
b00000000000000000000000000001010 ;
b00 C
b00000000000000000000000000001011 K
#85
b01 C
b11111111111111111111111111110111 K
#86
b10 C
b00000000000000000000000000001010 K
#87
b11 C
b00000000000000000000000000000000 K
#88
b00000000000000000000000000000010 3
b00000000000000000000000000000000 ;
b00 C
b00000000000000000000000000000010 K
#89
b01 C
#90
b10 C
b00000000000000000000000000000000 K
#91
b11 C
#92
b00000000000000000000000000000001 ;
b00 C
b00000000000000000000000000000011 K
#93
b01 C
b00000000000000000000000000000001 K
#94
b10 C
b00000000000000000000000000000010 K
#95
b11 C
b00000000000000000000000000000000 K
#96
b00000000000000000000000000000010 ;
b00 C
b00000000000000000000000000000100 K
#97
b01 C
b00000000000000000000000000000000 K
#98
b10 C
b00000000000000000000000000000100 K
#99
b11 C
b00000000000000000000000000000000 K
#100
b00000000000000000000000000000011 ;
b00 C
b00000000000000000000000000000101 K
#101
b01 C
b11111111111111111111111111111111 K
#102
b10 C
b00000000000000000000000000000110 K
#103
b11 C
b00000000000000000000000000000000 K
#104
b00000000000000000000000000000100 ;
b00 C
b00000000000000000000000000000110 K
#105
b01 C
b11111111111111111111111111111110 K
#106
b10 C
b00000000000000000000000000001000 K
#107
b11 C
b00000000000000000000000000000000 K
#108
b00000000000000000000000000000101 ;
b00 C
b00000000000000000000000000000111 K
#109
b01 C
b11111111111111111111111111111101 K
#110
b10 C
b00000000000000000000000000001010 K
#111
b11 C
b00000000000000000000000000000000 K
#112
b00000000000000000000000000000110 ;
b00 C
b00000000000000000000000000001000 K
#113
b01 C
b11111111111111111111111111111100 K
#114
b10 C
b00000000000000000000000000001100 K
#115
b11 C
b00000000000000000000000000000000 K
#116
b00000000000000000000000000000111 ;
b00 C
b00000000000000000000000000001001 K
#117
b01 C
b11111111111111111111111111111011 K
#118
b10 C
b00000000000000000000000000001110 K
#119
b11 C
b00000000000000000000000000000000 K
#120
b00000000000000000000000000001000 ;
b00 C
b00000000000000000000000000001010 K
#121
b01 C
b11111111111111111111111111111010 K
#122
b10 C
b00000000000000000000000000010000 K
#123
b11 C
b00000000000000000000000000000000 K
#124
b00000000000000000000000000001001 ;
b00 C
b00000000000000000000000000001011 K
#125
b01 C
b11111111111111111111111111111001 K
#126
b10 C
b00000000000000000000000000010010 K
#127
b11 C
b00000000000000000000000000000000 K
#128
b00000000000000000000000000001010 ;
b00 C
b00000000000000000000000000001100 K
#129
b01 C
b11111111111111111111111111111000 K
#130
b10 C
b00000000000000000000000000010100 K
#131
b11 C
b00000000000000000000000000000000 K
#132
b00000000000000000000000000000011 3
b00000000000000000000000000000000 ;
b00 C
b00000000000000000000000000000011 K
#133
b01 C
#134
b10 C
b00000000000000000000000000000000 K
#135
b11 C
#136
b00000000000000000000000000000001 ;
b00 C
b00000000000000000000000000000100 K
#137
b01 C
b00000000000000000000000000000010 K
#138
b10 C
b00000000000000000000000000000011 K
#139
b11 C
b00000000000000000000000000000000 K
#140
b00000000000000000000000000000010 ;
b00 C
b00000000000000000000000000000101 K
#141
b01 C
b00000000000000000000000000000001 K
#142
b10 C
b00000000000000000000000000000110 K
#143
b11 C
b00000000000000000000000000000000 K
#144
b00000000000000000000000000000011 ;
b00 C
b00000000000000000000000000000110 K
#145
b01 C
b00000000000000000000000000000000 K
#146
b10 C
b00000000000000000000000000001001 K
#147
b11 C
b00000000000000000000000000000000 K
#148
b00000000000000000000000000000100 ;
b00 C
b00000000000000000000000000000111 K
#149
b01 C
b11111111111111111111111111111111 K
#150
b10 C
b00000000000000000000000000001100 K
#151
b11 C
b00000000000000000000000000000000 K
#152
b00000000000000000000000000000101 ;
b00 C
b00000000000000000000000000001000 K
#153
b01 C
b11111111111111111111111111111110 K
#154
b10 C
b00000000000000000000000000001111 K
#155
b11 C
b00000000000000000000000000000000 K
#156
b00000000000000000000000000000110 ;
b00 C
b00000000000000000000000000001001 K
#157
b01 C
b11111111111111111111111111111101 K
#158
b10 C
b00000000000000000000000000010010 K
#159
b11 C
b00000000000000000000000000000000 K
#160
b00000000000000000000000000000111 ;
b00 C
b00000000000000000000000000001010 K
#161
b01 C
b11111111111111111111111111111100 K
#162
b10 C
b00000000000000000000000000010101 K
#163
b11 C
b00000000000000000000000000000000 K
#164
b00000000000000000000000000001000 ;
b00 C
b00000000000000000000000000001011 K
#165
b01 C
b11111111111111111111111111111011 K
#166
b10 C
b00000000000000000000000000011000 K
#167
b11 C
b00000000000000000000000000000000 K
#168
b00000000000000000000000000001001 ;
b00 C
b00000000000000000000000000001100 K
#169
b01 C
b11111111111111111111111111111010 K
#170
b10 C
b00000000000000000000000000011011 K
#171
b11 C
b00000000000000000000000000000000 K
#172
b00000000000000000000000000001010 ;
b00 C
b00000000000000000000000000001101 K
#173
b01 C
b11111111111111111111111111111001 K
#174
b10 C
b00000000000000000000000000011110 K
#175
b11 C
b00000000000000000000000000000000 K
#176
b00000000000000000000000000000100 3
b00000000000000000000000000000000 ;
b00 C
b00000000000000000000000000000100 K
#177
b01 C
#178
b10 C
b00000000000000000000000000000000 K
#179
b11 C
#180
b00000000000000000000000000000001 ;
b00 C
b00000000000000000000000000000101 K
#181
b01 C
b00000000000000000000000000000011 K
#182
b10 C
b00000000000000000000000000000100 K
#183
b11 C
b00000000000000000000000000000000 K
#184
b00000000000000000000000000000010 ;
b00 C
b00000000000000000000000000000110 K
#185
b01 C
b00000000000000000000000000000010 K
#186
b10 C
b00000000000000000000000000001000 K
#187
b11 C
b00000000000000000000000000000000 K
#188
b00000000000000000000000000000011 ;
b00 C
b00000000000000000000000000000111 K
#189
b01 C
b00000000000000000000000000000001 K
#190
b10 C
b00000000000000000000000000001100 K
#191
b11 C
b00000000000000000000000000000000 K
#192
b00000000000000000000000000000100 ;
b00 C
b00000000000000000000000000001000 K
#193
b01 C
b00000000000000000000000000000000 K
#194
b10 C
b00000000000000000000000000010000 K
#195
b11 C
b00000000000000000000000000000000 K
#196
b00000000000000000000000000000101 ;
b00 C
b00000000000000000000000000001001 K
#197
b01 C
b11111111111111111111111111111111 K
#198
b10 C
b00000000000000000000000000010100 K
#199
b11 C
b00000000000000000000000000000000 K
#200
b00000000000000000000000000000110 ;
b00 C
b00000000000000000000000000001010 K
#201
b01 C
b11111111111111111111111111111110 K
#202
b10 C
b00000000000000000000000000011000 K
#203
b11 C
b00000000000000000000000000000000 K
#204
b00000000000000000000000000000111 ;
b00 C
b00000000000000000000000000001011 K
#205
b01 C
b11111111111111111111111111111101 K
#206
b10 C
b00000000000000000000000000011100 K
#207
b11 C
b00000000000000000000000000000000 K
#208
b00000000000000000000000000001000 ;
b00 C
b00000000000000000000000000001100 K
#209
b01 C
b11111111111111111111111111111100 K
#210
b10 C
b00000000000000000000000000100000 K
#211
b11 C
b00000000000000000000000000000000 K
#212
b00000000000000000000000000001001 ;
b00 C
b00000000000000000000000000001101 K
#213
b01 C
b11111111111111111111111111111011 K
#214
b10 C
b00000000000000000000000000100100 K
#215
b11 C
b00000000000000000000000000000000 K
#216
b00000000000000000000000000001010 ;
b00 C
b00000000000000000000000000001110 K
#217
b01 C
b11111111111111111111111111111010 K
#218
b10 C
b00000000000000000000000000101000 K
#219
b11 C
b00000000000000000000000000000000 K
#220
b00000000000000000000000000000101 3
b00000000000000000000000000000000 ;
b00 C
b00000000000000000000000000000101 K
#221
b01 C
#222
b10 C
b00000000000000000000000000000000 K
#223
b11 C
#224
b00000000000000000000000000000001 ;
b00 C
b00000000000000000000000000000110 K
#225
b01 C
b00000000000000000000000000000100 K
#226
b10 C
b00000000000000000000000000000101 K
#227
b11 C
b00000000000000000000000000000000 K
#228
b00000000000000000000000000000010 ;
b00 C
b00000000000000000000000000000111 K
#229
b01 C
b00000000000000000000000000000011 K
#230
b10 C
b00000000000000000000000000001010 K
#231
b11 C
b00000000000000000000000000000000 K
#232
b00000000000000000000000000000011 ;
b00 C
b00000000000000000000000000001000 K
#233
b01 C
b00000000000000000000000000000010 K
#234
b10 C
b00000000000000000000000000001111 K
#235
b11 C
b00000000000000000000000000000000 K
#236
b00000000000000000000000000000100 ;
b00 C
b00000000000000000000000000001001 K
#237
b01 C
b00000000000000000000000000000001 K
#238
b10 C
b00000000000000000000000000010100 K
#239
b11 C
b00000000000000000000000000000000 K
#240
b00000000000000000000000000000101 ;
b00 C
b00000000000000000000000000001010 K
#241
b01 C
b00000000000000000000000000000000 K
#242
b10 C
b00000000000000000000000000011001 K
#243
b11 C
b00000000000000000000000000000000 K
#244
b00000000000000000000000000000110 ;
b00 C
b00000000000000000000000000001011 K
#245
b01 C
b11111111111111111111111111111111 K
#246
b10 C
b00000000000000000000000000011110 K
#247
b11 C
b00000000000000000000000000000000 K
#248
b00000000000000000000000000000111 ;
b00 C
b00000000000000000000000000001100 K
#249
b01 C
b11111111111111111111111111111110 K
#250
b10 C
b00000000000000000000000000100011 K
#251
b11 C
b00000000000000000000000000000000 K
#252
b00000000000000000000000000001000 ;
b00 C
b00000000000000000000000000001101 K
#253
b01 C
b11111111111111111111111111111101 K
#254
b10 C
b00000000000000000000000000101000 K
#255
b11 C
b00000000000000000000000000000000 K
#256
b00000000000000000000000000001001 ;
b00 C
b00000000000000000000000000001110 K
#257
b01 C
b11111111111111111111111111111100 K
#258
b10 C
b00000000000000000000000000101101 K
#259
b11 C
b00000000000000000000000000000000 K
#260
b00000000000000000000000000001010 ;
b00 C
b00000000000000000000000000001111 K
#261
b01 C
b11111111111111111111111111111011 K
#262
b10 C
b00000000000000000000000000110010 K
#263
b11 C
b00000000000000000000000000000000 K
#264
b00000000000000000000000000000110 3
b00000000000000000000000000000000 ;
b00 C
b00000000000000000000000000000110 K
#265
b01 C
#266
b10 C
b00000000000000000000000000000000 K
#267
b11 C
#268
b00000000000000000000000000000001 ;
b00 C
b00000000000000000000000000000111 K
#269
b01 C
b00000000000000000000000000000101 K
#270
b10 C
b00000000000000000000000000000110 K
#271
b11 C
b00000000000000000000000000000000 K
#272
b00000000000000000000000000000010 ;
b00 C
b00000000000000000000000000001000 K
#273
b01 C
b00000000000000000000000000000100 K
#274
b10 C
b00000000000000000000000000001100 K
#275
b11 C
b00000000000000000000000000000000 K
#276
b00000000000000000000000000000011 ;
b00 C
b00000000000000000000000000001001 K
#277
b01 C
b00000000000000000000000000000011 K
#278
b10 C
b00000000000000000000000000010010 K
#279
b11 C
b00000000000000000000000000000000 K
#280
b00000000000000000000000000000100 ;
b00 C
b00000000000000000000000000001010 K
#281
b01 C
b00000000000000000000000000000010 K
#282
b10 C
b00000000000000000000000000011000 K
#283
b11 C
b00000000000000000000000000000000 K
#284
b00000000000000000000000000000101 ;
b00 C
b00000000000000000000000000001011 K
#285
b01 C
b00000000000000000000000000000001 K
#286
b10 C
b00000000000000000000000000011110 K
#287
b11 C
b00000000000000000000000000000000 K
#288
b00000000000000000000000000000110 ;
b00 C
b00000000000000000000000000001100 K
#289
b01 C
b00000000000000000000000000000000 K
#290
b10 C
b00000000000000000000000000100100 K
#291
b11 C
b00000000000000000000000000000000 K
#292
b00000000000000000000000000000111 ;
b00 C
b00000000000000000000000000001101 K
#293
b01 C
b11111111111111111111111111111111 K
#294
b10 C
b00000000000000000000000000101010 K
#295
b11 C
b00000000000000000000000000000000 K
#296
b00000000000000000000000000001000 ;
b00 C
b00000000000000000000000000001110 K
#297
b01 C
b11111111111111111111111111111110 K
#298
b10 C
b00000000000000000000000000110000 K
#299
b11 C
b00000000000000000000000000000000 K
#300
b00000000000000000000000000001001 ;
b00 C
b00000000000000000000000000001111 K
#301
b01 C
b11111111111111111111111111111101 K
#302
b10 C
b00000000000000000000000000110110 K
#303
b11 C
b00000000000000000000000000000000 K
#304
b00000000000000000000000000001010 ;
b00 C
b00000000000000000000000000010000 K
#305
b01 C
b11111111111111111111111111111100 K
#306
b10 C
b00000000000000000000000000111100 K
#307
b11 C
b00000000000000000000000000000000 K
#308
b00000000000000000000000000000111 3
b00000000000000000000000000000000 ;
b00 C
b00000000000000000000000000000111 K
#309
b01 C
#310
b10 C
b00000000000000000000000000000000 K
#311
b11 C
#312
b00000000000000000000000000000001 ;
b00 C
b00000000000000000000000000001000 K
#313
b01 C
b00000000000000000000000000000110 K
#314
b10 C
b00000000000000000000000000000111 K
#315
b11 C
b00000000000000000000000000000000 K
#316
b00000000000000000000000000000010 ;
b00 C
b00000000000000000000000000001001 K
#317
b01 C
b00000000000000000000000000000101 K
#318
b10 C
b00000000000000000000000000001110 K
#319
b11 C
b00000000000000000000000000000000 K
#320
b00000000000000000000000000000011 ;
b00 C
b00000000000000000000000000001010 K
#321
b01 C
b00000000000000000000000000000100 K
#322
b10 C
b00000000000000000000000000010101 K
#323
b11 C
b00000000000000000000000000000000 K
#324
b00000000000000000000000000000100 ;
b00 C
b00000000000000000000000000001011 K
#325
b01 C
b00000000000000000000000000000011 K
#326
b10 C
b00000000000000000000000000011100 K
#327
b11 C
b00000000000000000000000000000000 K
#328
b00000000000000000000000000000101 ;
b00 C
b00000000000000000000000000001100 K
#329
b01 C
b00000000000000000000000000000010 K
#330
b10 C
b00000000000000000000000000100011 K
#331
b11 C
b00000000000000000000000000000000 K
#332
b00000000000000000000000000000110 ;
b00 C
b00000000000000000000000000001101 K
#333
b01 C
b00000000000000000000000000000001 K
#334
b10 C
b00000000000000000000000000101010 K
#335
b11 C
b00000000000000000000000000000000 K
#336
b00000000000000000000000000000111 ;
b00 C
b00000000000000000000000000001110 K
#337
b01 C
b00000000000000000000000000000000 K
#338
b10 C
b00000000000000000000000000110001 K
#339
b11 C
b00000000000000000000000000000000 K
#340
b00000000000000000000000000001000 ;
b00 C
b00000000000000000000000000001111 K
#341
b01 C
b11111111111111111111111111111111 K
#342
b10 C
b00000000000000000000000000111000 K
#343
b11 C
b00000000000000000000000000000000 K
#344
b00000000000000000000000000001001 ;
b00 C
b00000000000000000000000000010000 K
#345
b01 C
b11111111111111111111111111111110 K
#346
b10 C
b00000000000000000000000000111111 K
#347
b11 C
b00000000000000000000000000000000 K
#348
b00000000000000000000000000001010 ;
b00 C
b00000000000000000000000000010001 K
#349
b01 C
b11111111111111111111111111111101 K
#350
b10 C
b00000000000000000000000001000110 K
#351
b11 C
b00000000000000000000000000000000 K
#352
b00000000000000000000000000001000 3
b00000000000000000000000000000000 ;
b00 C
b00000000000000000000000000001000 K
#353
b01 C
#354
b10 C
b00000000000000000000000000000000 K
#355
b11 C
#356
b00000000000000000000000000000001 ;
b00 C
b00000000000000000000000000001001 K
#357
b01 C
b00000000000000000000000000000111 K
#358
b10 C
b00000000000000000000000000001000 K
#359
b11 C
b00000000000000000000000000000000 K
#360
b00000000000000000000000000000010 ;
b00 C
b00000000000000000000000000001010 K
#361
b01 C
b00000000000000000000000000000110 K
#362
b10 C
b00000000000000000000000000010000 K
#363
b11 C
b00000000000000000000000000000000 K
#364
b00000000000000000000000000000011 ;
b00 C
b00000000000000000000000000001011 K
#365
b01 C
b00000000000000000000000000000101 K
#366
b10 C
b00000000000000000000000000011000 K
#367
b11 C
b00000000000000000000000000000000 K
#368
b00000000000000000000000000000100 ;
b00 C
b00000000000000000000000000001100 K
#369
b01 C
b00000000000000000000000000000100 K
#370
b10 C
b00000000000000000000000000100000 K
#371
b11 C
b00000000000000000000000000000000 K
#372
b00000000000000000000000000000101 ;
b00 C
b00000000000000000000000000001101 K
#373
b01 C
b00000000000000000000000000000011 K
#374
b10 C
b00000000000000000000000000101000 K
#375
b11 C
b00000000000000000000000000000000 K
#376
b00000000000000000000000000000110 ;
b00 C
b00000000000000000000000000001110 K
#377
b01 C
b00000000000000000000000000000010 K
#378
b10 C
b00000000000000000000000000110000 K
#379
b11 C
b00000000000000000000000000000000 K
#380
b00000000000000000000000000000111 ;
b00 C
b00000000000000000000000000001111 K
#381
b01 C
b00000000000000000000000000000001 K
#382
b10 C
b00000000000000000000000000111000 K
#383
b11 C
b00000000000000000000000000000000 K
#384
b00000000000000000000000000001000 ;
b00 C
b00000000000000000000000000010000 K
#385
b01 C
b00000000000000000000000000000000 K
#386
b10 C
b00000000000000000000000001000000 K
#387
b11 C
b00000000000000000000000000000000 K
#388
b00000000000000000000000000001001 ;
b00 C
b00000000000000000000000000010001 K
#389
b01 C
b11111111111111111111111111111111 K
#390
b10 C
b00000000000000000000000001001000 K
#391
b11 C
b00000000000000000000000000000000 K
#392
b00000000000000000000000000001010 ;
b00 C
b00000000000000000000000000010010 K
#393
b01 C
b11111111111111111111111111111110 K
#394
b10 C
b00000000000000000000000001010000 K
#395
b11 C
b00000000000000000000000000000000 K
#396
b00000000000000000000000000001001 3
b00000000000000000000000000000000 ;
b00 C
b00000000000000000000000000001001 K
#397
b01 C
#398
b10 C
b00000000000000000000000000000000 K
#399
b11 C
#400
b00000000000000000000000000000001 ;
b00 C
b00000000000000000000000000001010 K
#401
b01 C
b00000000000000000000000000001000 K
#402
b10 C
b00000000000000000000000000001001 K
#403
b11 C
b00000000000000000000000000000000 K
#404
b00000000000000000000000000000010 ;
b00 C
b00000000000000000000000000001011 K
#405
b01 C
b00000000000000000000000000000111 K
#406
b10 C
b00000000000000000000000000010010 K
#407
b11 C
b00000000000000000000000000000000 K
#408
b00000000000000000000000000000011 ;
b00 C
b00000000000000000000000000001100 K
#409
b01 C
b00000000000000000000000000000110 K
#410
b10 C
b00000000000000000000000000011011 K
#411
b11 C
b00000000000000000000000000000000 K
#412
b00000000000000000000000000000100 ;
b00 C
b00000000000000000000000000001101 K
#413
b01 C
b00000000000000000000000000000101 K
#414
b10 C
b00000000000000000000000000100100 K
#415
b11 C
b00000000000000000000000000000000 K
#416
b00000000000000000000000000000101 ;
b00 C
b00000000000000000000000000001110 K
#417
b01 C
b00000000000000000000000000000100 K
#418
b10 C
b00000000000000000000000000101101 K
#419
b11 C
b00000000000000000000000000000000 K
#420
b00000000000000000000000000000110 ;
b00 C
b00000000000000000000000000001111 K
#421
b01 C
b00000000000000000000000000000011 K
#422
b10 C
b00000000000000000000000000110110 K
#423
b11 C
b00000000000000000000000000000000 K
#424
b00000000000000000000000000000111 ;
b00 C
b00000000000000000000000000010000 K
#425
b01 C
b00000000000000000000000000000010 K
#426
b10 C
b00000000000000000000000000111111 K
#427
b11 C
b00000000000000000000000000000000 K
#428
b00000000000000000000000000001000 ;
b00 C
b00000000000000000000000000010001 K
#429
b01 C
b00000000000000000000000000000001 K
#430
b10 C
b00000000000000000000000001001000 K
#431
b11 C
b00000000000000000000000000000000 K
#432
b00000000000000000000000000001001 ;
b00 C
b00000000000000000000000000010010 K
#433
b01 C
b00000000000000000000000000000000 K
#434
b10 C
b00000000000000000000000001010001 K
#435
b11 C
b00000000000000000000000000000000 K
#436
b00000000000000000000000000001010 ;
b00 C
b00000000000000000000000000010011 K
#437
b01 C
b11111111111111111111111111111111 K
#438
b10 C
b00000000000000000000000001011010 K
#439
b11 C
b00000000000000000000000000000000 K
#440
b00000000000000000000000000001010 3
b00000000000000000000000000000000 ;
b00 C
b00000000000000000000000000001010 K
#441
b01 C
#442
b10 C
b00000000000000000000000000000000 K
#443
b11 C
#444
b00000000000000000000000000000001 ;
b00 C
b00000000000000000000000000001011 K
#445
b01 C
b00000000000000000000000000001001 K
#446
b10 C
b00000000000000000000000000001010 K
#447
b11 C
b00000000000000000000000000000000 K
#448
b00000000000000000000000000000010 ;
b00 C
b00000000000000000000000000001100 K
#449
b01 C
b00000000000000000000000000001000 K
#450
b10 C
b00000000000000000000000000010100 K
#451
b11 C
b00000000000000000000000000000000 K
#452
b00000000000000000000000000000011 ;
b00 C
b00000000000000000000000000001101 K
#453
b01 C
b00000000000000000000000000000111 K
#454
b10 C
b00000000000000000000000000011110 K
#455
b11 C
b00000000000000000000000000000000 K
#456
b00000000000000000000000000000100 ;
b00 C
b00000000000000000000000000001110 K
#457
b01 C
b00000000000000000000000000000110 K
#458
b10 C
b00000000000000000000000000101000 K
#459
b11 C
b00000000000000000000000000000000 K
#460
b00000000000000000000000000000101 ;
b00 C
b00000000000000000000000000001111 K
#461
b01 C
b00000000000000000000000000000101 K
#462
b10 C
b00000000000000000000000000110010 K
#463
b11 C
b00000000000000000000000000000000 K
#464
b00000000000000000000000000000110 ;
b00 C
b00000000000000000000000000010000 K
#465
b01 C
b00000000000000000000000000000100 K
#466
b10 C
b00000000000000000000000000111100 K
#467
b11 C
b00000000000000000000000000000000 K
#468
b00000000000000000000000000000111 ;
b00 C
b00000000000000000000000000010001 K
#469
b01 C
b00000000000000000000000000000011 K
#470
b10 C
b00000000000000000000000001000110 K
#471
b11 C
b00000000000000000000000000000000 K
#472
b00000000000000000000000000001000 ;
b00 C
b00000000000000000000000000010010 K
#473
b01 C
b00000000000000000000000000000010 K
#474
b10 C
b00000000000000000000000001010000 K
#475
b11 C
b00000000000000000000000000000000 K
#476
b00000000000000000000000000001001 ;
b00 C
b00000000000000000000000000010011 K
#477
b01 C
b00000000000000000000000000000001 K
#478
b10 C
b00000000000000000000000001011010 K
#479
b11 C
b00000000000000000000000000000000 K
#480
b00000000000000000000000000001010 ;
b00 C
b00000000000000000000000000010100 K
#481
b01 C
b00000000000000000000000000000000 K
#482
b10 C
b00000000000000000000000001100100 K
#483
b11 C
b00000000000000000000000000000000 K
#484
b00000000000000000000000000000000 3
b00000000000000000000000000000000 ;
b00 C
#485
b01 C
#486
b10 C
#487
b11 C
#488
b00000000000000000000000000000001 ;
b00 C
b00000000000000000000000000000001 K
#489
b01 C
b11111111111111111111111111111111 K
#490
b10 C
b00000000000000000000000000000000 K
#491
b11 C
#492
b00000000000000000000000000000010 ;
b00 C
b00000000000000000000000000000010 K
#493
b01 C
b11111111111111111111111111111110 K
#494
b10 C
b00000000000000000000000000000000 K
#495
b11 C
#496
b00000000000000000000000000000011 ;
b00 C
b00000000000000000000000000000011 K
#497
b01 C
b11111111111111111111111111111101 K
#498
b10 C
b00000000000000000000000000000000 K
#499
b11 C
#500
b00000000000000000000000000000100 ;
b00 C
b00000000000000000000000000000100 K
#501
b01 C
b11111111111111111111111111111100 K
#502
b10 C
b00000000000000000000000000000000 K
#503
b11 C
#504
b00000000000000000000000000000101 ;
b00 C
b00000000000000000000000000000101 K
#505
b01 C
b11111111111111111111111111111011 K
#506
b10 C
b00000000000000000000000000000000 K
#507
b11 C
#508
b00000000000000000000000000000110 ;
b00 C
b00000000000000000000000000000110 K
#509
b01 C
b11111111111111111111111111111010 K
#510
b10 C
b00000000000000000000000000000000 K
#511
b11 C
#512
b00000000000000000000000000000111 ;
b00 C
b00000000000000000000000000000111 K
#513
b01 C
b11111111111111111111111111111001 K
#514
b10 C
b00000000000000000000000000000000 K
#515
b11 C
#516
b00000000000000000000000000001000 ;
b00 C
b00000000000000000000000000001000 K
#517
b01 C
b11111111111111111111111111111000 K
#518
b10 C
b00000000000000000000000000000000 K
#519
b11 C
#520
b00000000000000000000000000001001 ;
b00 C
b00000000000000000000000000001001 K
#521
b01 C
b11111111111111111111111111110111 K
#522
b10 C
b00000000000000000000000000000000 K
#523
b11 C
#524
b00000000000000000000000000001010 ;
b00 C
b00000000000000000000000000001010 K
#525
b01 C
b11111111111111111111111111110110 K
#526
b10 C
b00000000000000000000000000000000 K
#527
b11 C
#528
b00000000000000000000000000000001 3
b00000000000000000000000000000000 ;
b00 C
b00000000000000000000000000000001 K
#529
b01 C
#530
b10 C
b00000000000000000000000000000000 K
#531
b11 C
#532
b00000000000000000000000000000001 ;
b00 C
b00000000000000000000000000000010 K
#533
b01 C
b00000000000000000000000000000000 K
#534
b10 C
b00000000000000000000000000000001 K
#535
b11 C
b00000000000000000000000000000000 K
#536
b00000000000000000000000000000010 ;
b00 C
b00000000000000000000000000000011 K
#537
b01 C
b11111111111111111111111111111111 K
#538
b10 C
b00000000000000000000000000000010 K
#539
b11 C
b00000000000000000000000000000000 K
#540
b00000000000000000000000000000011 ;
b00 C
b00000000000000000000000000000100 K
#541
b01 C
b11111111111111111111111111111110 K
#542
b10 C
b00000000000000000000000000000011 K
#543
b11 C
b00000000000000000000000000000000 K
#544
b00000000000000000000000000000100 ;
b00 C
b00000000000000000000000000000101 K
