MUL.v
module MUL(
  input        clock,
  input        reset,
  input  [3:0] io_multiplier,
  input  [3:0] io_multiplicand,
  output [7:0] io_product,
  input        io_inputValid,
  output       io_outputValid
);
`ifdef RANDOMIZE_REG_INIT
  reg [31:0] _RAND_0;
  reg [31:0] _RAND_1;
  reg [31:0] _RAND_2;
  reg [31:0] _RAND_3;
`endif // RANDOMIZE_REG_INIT
  reg [7:0] multiplicandReg; // @[MUL.scala 23:34]
  reg [3:0] multiplierReg; // @[MUL.scala 24:32]
  reg [7:0] productReg; // @[MUL.scala 25:29]
  reg [2:0] cntReg; // @[MUL.scala 26:25]
  wire [7:0] _productReg_T_1 = productReg + multiplicandReg; // @[MUL.scala 30:38]
  wire [3:0] _multiplierReg_T = {{1'd0}, multiplierReg[3:1]}; // @[MUL.scala 32:40]
  wire [8:0] _multiplicandReg_T = {multiplicandReg, 1'h0}; // @[MUL.scala 33:44]
  wire [2:0] _cntReg_T_1 = cntReg - 3'h1; // @[MUL.scala 34:26]
  wire [7:0] _multiplicandReg_T_1 = {4'h0,io_multiplicand}; // @[Cat.scala 30:58]
  wire [7:0] _GEN_1 = io_inputValid ? _multiplicandReg_T_1 : multiplicandReg; // @[MUL.scala 36:29 MUL.scala 37:29 MUL.scala 23:34]
  wire [7:0] _GEN_5 = cntReg == 3'h0 ? _GEN_1 : multiplicandReg; // @[MUL.scala 35:32 MUL.scala 23:34]
  wire [8:0] _GEN_11 = cntReg != 3'h0 ? _multiplicandReg_T : {{1'd0}, _GEN_5}; // @[MUL.scala 28:26 MUL.scala 33:25]
  assign io_product = productReg; // @[MUL.scala 45:16]
  assign io_outputValid = cntReg == 3'h0; // @[MUL.scala 44:31]
  always @(posedge clock) begin
    if (reset) begin // @[MUL.scala 23:34]
      multiplicandReg <= 8'h0; // @[MUL.scala 23:34]
    end else begin
      multiplicandReg <= _GEN_11[7:0];
    end
    if (reset) begin // @[MUL.scala 24:32]
      multiplierReg <= 4'h0; // @[MUL.scala 24:32]
    end else if (cntReg != 3'h0) begin // @[MUL.scala 28:26]
      multiplierReg <= _multiplierReg_T; // @[MUL.scala 32:23]
    end else if (cntReg == 3'h0) begin // @[MUL.scala 35:32]
      if (io_inputValid) begin // @[MUL.scala 36:29]
        multiplierReg <= io_multiplier; // @[MUL.scala 38:27]
      end
    end
    if (reset) begin // @[MUL.scala 25:29]
      productReg <= 8'h0; // @[MUL.scala 25:29]
    end else if (cntReg != 3'h0) begin // @[MUL.scala 28:26]
      if (multiplierReg[0]) begin // @[MUL.scala 29:40]
        productReg <= _productReg_T_1; // @[MUL.scala 30:24]
      end
    end else if (cntReg == 3'h0) begin // @[MUL.scala 35:32]
      if (io_inputValid) begin // @[MUL.scala 36:29]
        productReg <= 8'h0; // @[MUL.scala 39:24]
      end
    end
    if (reset) begin // @[MUL.scala 26:25]
      cntReg <= 3'h0; // @[MUL.scala 26:25]
    end else if (cntReg != 3'h0) begin // @[MUL.scala 28:26]
      cntReg <= _cntReg_T_1; // @[MUL.scala 34:16]
    end else if (cntReg == 3'h0) begin // @[MUL.scala 35:32]
      if (io_inputValid) begin // @[MUL.scala 36:29]
        cntReg <= 3'h4; // @[MUL.scala 40:20]
      end
    end
  end
// Register and memory initialization
`ifdef RANDOMIZE_GARBAGE_ASSIGN
`define RANDOMIZE
`endif
`ifdef RANDOMIZE_INVALID_ASSIGN
`define RANDOMIZE
`endif
`ifdef RANDOMIZE_REG_INIT
`define RANDOMIZE
`endif
`ifdef RANDOMIZE_MEM_INIT
`define RANDOMIZE
`endif
`ifndef RANDOM
`define RANDOM $random
`endif
`ifdef RANDOMIZE_MEM_INIT
  integer initvar;
`endif
`ifndef SYNTHESIS
`ifdef FIRRTL_BEFORE_INITIAL
`FIRRTL_BEFORE_INITIAL
`endif
initial begin
  `ifdef RANDOMIZE
    `ifdef INIT_RANDOM
      `INIT_RANDOM
    `endif
    `ifndef VERILATOR
      `ifdef RANDOMIZE_DELAY
        #`RANDOMIZE_DELAY begin end
      `else
        #0.002 begin end
      `endif
    `endif
`ifdef RANDOMIZE_REG_INIT
  _RAND_0 = {1{`RANDOM}};
  multiplicandReg = _RAND_0[7:0];
  _RAND_1 = {1{`RANDOM}};
  multiplierReg = _RAND_1[3:0];
  _RAND_2 = {1{`RANDOM}};
  productReg = _RAND_2[7:0];
  _RAND_3 = {1{`RANDOM}};
  cntReg = _RAND_3[2:0];
`endif // RANDOMIZE_REG_INIT
  `endif // RANDOMIZE
end // initial
`ifdef FIRRTL_AFTER_INITIAL
`FIRRTL_AFTER_INITIAL
`endif
`endif // SYNTHESIS
endmodule

VMUL.vcd
$version Generated by VerilatedVcd $end
$date Sun Nov 21 11:51:53 2021
 $end
$timescale   1ns $end

 $scope module TOP $end
  $var wire  1 C clock $end
  $var wire  1 k io_inputValid $end
  $var wire  4 [ io_multiplicand [3:0] $end
  $var wire  4 S io_multiplier [3:0] $end
  $var wire  1 s io_outputValid $end
  $var wire  8 c io_product [7:0] $end
  $var wire  1 K reset $end
  $scope module MUL $end
   $var wire  1 C clock $end
   $var wire  3 ; cntReg [2:0] $end
   $var wire  1 k io_inputValid $end
   $var wire  4 [ io_multiplicand [3:0] $end
   $var wire  4 S io_multiplier [3:0] $end
   $var wire  1 s io_outputValid $end
   $var wire  8 c io_product [7:0] $end
   $var wire  8 # multiplicandReg [7:0] $end
   $var wire  4 + multiplierReg [3:0] $end
   $var wire  8 3 productReg [7:0] $end
   $var wire  1 K reset $end
  $upscope $end
 $upscope $end
$enddefinitions $end


#0
b00000000 #
b0000 +
b00000000 3
b000 ;
0C
0K
b0000 S
b0000 [
b00000000 c
1k
1s
#1
b100 ;
1C
0s
#2
0C
0k
#3
b011 ;
1C
#4
0C
#5
b010 ;
1C
#6
0C
#7
b001 ;
1C
#8
0C
#9
b000 ;
1C
1s
#10
0C
b0001 [
1k
#11
b00000001 #
b100 ;
1C
0s
#12
0C
0k
#13
b00000010 #
b011 ;
1C
#14
0C
#15
b00000100 #
b010 ;
1C
#16
0C
#17
b00001000 #
b001 ;
1C
#18
0C
#19
b00010000 #
b000 ;
1C
1s
#20
0C
b0010 [
1k
#21
b00000010 #
b100 ;
1C
0s
#22
0C
0k
#23
b00000100 #
b011 ;
1C
#24
0C
#25
b00001000 #
b010 ;
1C
#26
0C
#27
b00010000 #
b001 ;
1C
#28
0C
#29
b00100000 #
b000 ;
1C
1s
#30
0C
b0011 [
1k
#31
b00000011 #
b100 ;
1C
0s
#32
0C
0k
#33
b00000110 #
b011 ;
1C
#34
0C
#35
b00001100 #
b010 ;
1C
#36
0C
#37
b00011000 #
b001 ;
1C
#38
0C
#39
b00110000 #
b000 ;
1C
1s
#40
0C
b0100 [
1k
#41
b00000100 #
b100 ;
1C
0s
#42
0C
0k
#43
b00001000 #
b011 ;
1C
#44
0C
#45
b00010000 #
b010 ;
1C
#46
0C
#47
b00100000 #
b001 ;
1C
#48
0C
#49
b01000000 #
b000 ;
1C
1s
#50
0C
b0101 [
1k
#51
b00000101 #
b100 ;
1C
0s
#52
0C
0k
#53
b00001010 #
b011 ;
1C
#54
0C
#55
b00010100 #
b010 ;
1C
#56
0C
#57
b00101000 #
b001 ;
1C
#58
0C
#59
b01010000 #
b000 ;
1C
1s
#60
0C
b0110 [
1k
#61
b00000110 #
b100 ;
1C
0s
#62
0C
0k
#63
b00001100 #
b011 ;
1C
#64
0C
#65
b00011000 #
b010 ;
1C
#66
0C
#67
b00110000 #
b001 ;
1C
#68
0C
#69
b01100000 #
b000 ;
1C
1s
#70
0C
b0111 [
1k
#71
b00000111 #
b100 ;
1C
0s
#72
0C
0k
#73
b00001110 #
b011 ;
1C
#74
0C
#75
b00011100 #
b010 ;
1C
#76
0C
#77
b00111000 #
b001 ;
1C
#78
0C
#79
b01110000 #
b000 ;
1C
1s
#80
0C
b1000 [
1k
#81
b00001000 #
b100 ;
1C
0s
#82
0C
0k
#83
b00010000 #
b011 ;
1C
#84
0C
#85
b00100000 #
b010 ;
1C
#86
0C
#87
b01000000 #
b001 ;
1C
#88
0C
#89
b10000000 #
b000 ;
1C
1s
#90
0C
b1001 [
1k
#91
b00001001 #
b100 ;
1C
0s
#92
0C
0k
#93
b00010010 #
b011 ;
1C
#94
0C
#95
b00100100 #
b010 ;
1C
#96
0C
#97
b01001000 #
b001 ;
1C
#98
0C
#99
b10010000 #
b000 ;
1C
1s
#100
0C
b1010 [
1k
#101
b00001010 #
b100 ;
1C
0s
#102
0C
0k
#103
b00010100 #
b011 ;
1C
#104
0C
#105
b00101000 #
b010 ;
1C
#106
0C
#107
b01010000 #
b001 ;
1C
#108
0C
#109
b10100000 #
b000 ;
1C
1s
#110
0C
b1011 [
1k
#111
b00001011 #
b100 ;
1C
0s
#112
0C
0k
#113
b00010110 #
b011 ;
1C
#114
0C
#115
b00101100 #
b010 ;
1C
#116
0C
#117
b01011000 #
b001 ;
1C
#118
0C
#119
b10110000 #
b000 ;
1C
1s
#120
0C
b1100 [
1k
#121
b00001100 #
b100 ;
1C
0s
#122
0C
0k
#123
b00011000 #
b011 ;
1C
#124
0C
#125
b00110000 #
b010 ;
1C
#126
0C
#127
b01100000 #
b001 ;
1C
#128
0C
#129
b11000000 #
b000 ;
1C
1s
#130
0C
b1101 [
1k
#131
b00001101 #
b100 ;
1C
0s
#132
0C
0k
#133
b00011010 #
b011 ;
1C
#134
0C
#135
b00110100 #
b010 ;
1C
#136
0C
#137
b01101000 #
b001 ;
1C
#138
0C
#139
b11010000 #
b000 ;
1C
1s
#140
0C
b1110 [
1k
#141
b00001110 #
b100 ;
1C
0s
#142
0C
0k
#143
b00011100 #
b011 ;
1C
#144
0C
#145
b00111000 #
b010 ;
1C
#146
0C
#147
b01110000 #
b001 ;
1C
#148
0C
#149
b11100000 #
b000 ;
1C
1s
#150
0C
b1111 [
1k
#151
b00001111 #
b100 ;
1C
0s
#152
0C
0k
#153
b00011110 #
b011 ;
1C
#154
0C
#155
b00111100 #
b010 ;
1C
#156
0C
#157
b01111000 #
b001 ;
1C
#158
0C
#159
b11110000 #
b000 ;
1C
1s
#160
0C
b0001 S
b0000 [
1k
#161
b00000000 #
b0001 +
b100 ;
1C
0s
#162
0C
0k
#163
b0000 +
b011 ;
1C
#164
0C
#165
b010 ;
1C
#166
0C
#167
b001 ;
1C
#168
0C
#169
b000 ;
1C
1s
#170
0C
b0001 [
1k
#171
b00000001 #
b0001 +
b100 ;
1C
0s
#172
0C
0k
#173
b00000010 #
b0000 +
b00000001 3
b011 ;
1C
b00000001 c
#174
0C
#175
b00000100 #
b010 ;
1C
#176
0C
#177
b00001000 #
b001 ;
1C
#178
0C
#179
b00010000 #
b000 ;
1C
1s
#180
0C
b0010 [
1k
#181
b00000010 #
b0001 +
b00000000 3
b100 ;
1C
b00000000 c
0s
#182
0C
0k
#183
b00000100 #
b0000 +
b00000010 3
b011 ;
1C
b00000010 c
#184
0C
#185
b00001000 #
b010 ;
1C
#186
0C
#187
b00010000 #
b001 ;
1C
#188
0C
#189
b00100000 #
b000 ;
1C
1s
#190
0C
b0011 [
1k
#191
b00000011 #
b0001 +
b00000000 3
b100 ;
1C
b00000000 c
0s
#192
0C
0k
#193
b00000110 #
b0000 +
b00000011 3
b011 ;
1C
b00000011 c
#194
0C
#195
b00001100 #
b010 ;
1C
#196
0C
#197
b00011000 #
b001 ;
1C
#198
0C
#199
b00110000 #
b000 ;
1C
1s
#200
0C
b0100 [
1k
#201
b00000100 #
b0001 +
b00000000 3
b100 ;
1C
b00000000 c
0s
#202
0C
0k
#203
b00001000 #
b0000 +
b00000100 3
b011 ;
1C
b00000100 c
#204
0C
#205
b00010000 #
b010 ;
1C
#206
0C
#207
b00100000 #
b001 ;
1C
#208
0C
#209
b01000000 #
b000 ;
1C
1s
#210
0C
b0101 [
1k
#211
b00000101 #
b0001 +
b00000000 3
b100 ;
1C
b00000000 c
0s
#212
0C
0k
#213
b00001010 #
b0000 +
b00000101 3
b011 ;
1C
b00000101 c
#214
0C
#215
b00010100 #
b010 ;
1C
#216
0C
#217
b00101000 #
b001 ;
1C
#218
0C
#219
b01010000 #
b000 ;
1C
1s
#220
0C
b0110 [
1k
#221
b00000110 #
b0001 +
b00000000 3
b100 ;
1C
b00000000 c
0s
#222
0C
0k
#223
b00001100 #
b0000 +
b00000110 3
b011 ;
1C
b00000110 c
#224
0C
#225
b00011000 #
b010 ;
1C
#226
0C
#227
b00110000 #
b001 ;
1C
#228
0C
#229
b01100000 #
b000 ;
1C
1s
#230
0C
b0111 [
1k
#231
b00000111 #
b0001 +
b00000000 3
b100 ;
1C
b00000000 c
0s
#232
0C
0k
#233
b00001110 #
b0000 +
b00000111 3
b011 ;
1C
b00000111 c
#234
0C
#235
b00011100 #
b010 ;
1C
#236
0C
#237
b00111000 #
b001 ;
1C
#238
0C
#239
b01110000 #
b000 ;
1C
1s
#240
0C
b1000 [
1k
#241
b00001000 #
b0001 +
b00000000 3
b100 ;
1C
b00000000 c
0s
#242
0C
0k
#243
b00010000 #
b0000 +
b00001000 3
b011 ;
1C
b00001000 c
#244
0C
#245
b00100000 #
b010 ;
1C
#246
0C
#247
b01000000 #
b001 ;
1C
#248
0C
#249
b10000000 #
b000 ;
1C
1s
#250
0C
b1001 [
1k
#251
b00001001 #
b0001 +
b00000000 3
b100 ;
1C
b00000000 c
0s
#252
0C
0k
#253
b00010010 #
b0000 +
b00001001 3
b011 ;
1C
b00001001 c
#254
0C
#255
b00100100 #
b010 ;
1C
#256
0C
#257
b01001000 #
b001 ;
1C
#258
0C
#259
b10010000 #
b000 ;
1C
1s
#260
0C
b1010 [
1k
#261
b00001010 #
b0001 +
b00000000 3
b100 ;
1C
b00000000 c
0s
#262
0C
0k
#263
b00010100 #
b0000 +
b00001010 3
b011 ;
1C
b00001010 c
#264
0C
#265
b00101000 #
b010 ;
1C
#266
0C
#267
b01010000 #
b001 ;
1C
#268
0C
#269
b10100000 #
b000 ;
1C
1s
#270
0C
b1011 [
1k
#271
b00001011 #
b0001 +
b00000000 3
b100 ;
1C
b00000000 c
0s
#272
0C
0k
#273
b00010110 #
b0000 +
b00001011 3
b011 ;
1C
b00001011 c
#274
0C
#275
b00101100 #
b010 ;
1C
#276
0C
#277
b01011000 #
b001 ;
1C
#278
0C
#279
b10110000 #
b000 ;
1C
1s
#280
0C
b1100 [
1k
#281
b00001100 #
b0001 +
b00000000 3
b100 ;
1C
b00000000 c
0s
#282
0C
0k
#283
b00011000 #
b0000 +
b00001100 3
b011 ;
1C
b00001100 c
#284
0C
#285
b00110000 #
b010 ;
1C
#286
0C
#287
b01100000 #
b001 ;
1C
#288
0C
#289
b11000000 #
b000 ;
1C
1s
#290
0C
b1101 [
1k
#291
b00001101 #
b0001 +
b00000000 3
b100 ;
1C
b00000000 c
0s
#292
0C
0k
#293
b00011010 #
b0000 +
b00001101 3
b011 ;
1C
b00001101 c
#294
0C
#295
b00110100 #
b010 ;
1C
#296
0C
#297
b01101000 #
b001 ;
1C
#298
0C
#299
b11010000 #
b000 ;
1C
1s
#300
0C
b1110 [
1k
#301
b00001110 #
b0001 +
b00000000 3
b100 ;
1C
b00000000 c
0s
#302
0C
0k
#303
b00011100 #
b0000 +
b00001110 3
b011 ;
1C
b00001110 c
#304
0C
#305
b00111000 #
b010 ;
1C
#306
0C
#307
b01110000 #
b001 ;
1C
#308
0C
#309
b11100000 #
b000 ;
1C
1s
#310
0C
b1111 [
1k
#311
b00001111 #
b0001 +
b00000000 3
b100 ;
1C
b00000000 c
0s
#312
0C
0k
#313
b00011110 #
b0000 +
b00001111 3
b011 ;
1C
b00001111 c
#314
0C
#315
b00111100 #
b010 ;
1C
#316
0C
#317
b01111000 #
b001 ;
1C
#318
0C
#319
b11110000 #
b000 ;
1C
1s
#320
0C
b0010 S
b0000 [
1k
#321
b00000000 #
b0010 +
b00000000 3
b100 ;
1C
b00000000 c
0s
#322
0C
0k
#323
b0001 +
b011 ;
1C
#324
0C
#325
b0000 +
b010 ;
1C
#326
0C
#327
b001 ;
1C
#328
0C
#329
b000 ;
1C
1s
#330
0C
b0001 [
1k
#331
b00000001 #
b0010 +
b100 ;
1C
0s
#332
0C
0k
#333
b00000010 #
b0001 +
b011 ;
1C
#334
0C
#335
b00000100 #
b0000 +
b00000010 3
b010 ;
1C
b00000010 c
#336
0C
#337
b00001000 #
b001 ;
1C
#338
0C
#339
b00010000 #
b000 ;
1C
1s
#340
0C
b0010 [
1k
#341
b00000010 #
b0010 +
b00000000 3
b100 ;
1C
b00000000 c
0s
#342
0C
0k
#343
b00000100 #
b0001 +
b011 ;
1C
#344
0C
#345
b00001000 #
b0000 +
b00000100 3
b010 ;
1C
b00000100 c
#346
0C
#347
b00010000 #
b001 ;
1C
#348
0C
#349
b00100000 #
b000 ;
1C
1s
#350
0C
b0011 [
1k
#351
b00000011 #
b0010 +
b00000000 3
b100 ;
1C
b00000000 c
0s
#352
0C
0k
#353
b00000110 #
b0001 +
b011 ;
1C
#354
0C
#355
b00001100 #
b0000 +
b00000110 3
b010 ;
1C
b00000110 c
#356
0C
#357
b00011000 #
b001 ;
1C
#358
0C
#359
b00110000 #
b000 ;
1C
1s
#360
0C
b0100 [
1k
#361
b00000100 #
b0010 +
b00000000 3
b100 ;
1C
b00000000 c
0s
#362
0C
0k
#363
b00001000 #
b0001 +
b011 ;
1C
#364
0C
#365
b00010000 #
b0000 +
b00001000 3
b010 ;
1C
b00001000 c
#366
0C
#367
b00100000 #
b001 ;
1C
#368
0C
#369
b01000000 #
b000 ;
1C
1s
#370
0C
b0101 [
1k
#371
b00000101 #
b0010 +
b00000000 3
b100 ;
1C
b00000000 c
0s
#372
0C
0k
#373
b00001010 #
b0001 +
b011 ;
1C
#374
0C
#375
b00010100 #
b0000 +
b00001010 3
b010 ;
1C
b00001010 c
#376
0C
#377
b00101000 #
b001 ;
1C
#378
0C
#379
b01010000 #
b000 ;
1C
1s
#380
0C
b0110 [
1k
#381
b00000110 #
b0010 +
b00000000 3
b100 ;
1C
b00000000 c
0s
#382
0C
0k
#383
b00001100 #
b0001 +
b011 ;
1C
#384
0C
#385
b00011000 #
b0000 +
b00001100 3
b010 ;
1C
b00001100 c
#386
0C
#387
b00110000 #
b001 ;
1C
#388
0C
#389
b01100000 #
b000 ;
1C
1s
#390
0C
b0111 [
1k
#391
b00000111 #
b0010 +
b00000000 3
b100 ;
1C
b00000000 c
0s
#392
0C
0k
#393
b00001110 #
b0001 +
b011 ;
1C
#394
0C
#395
b00011100 #
b0000 +
b00001110 3
b010 ;
1C
b00001110 c
#396
0C
#397
b00111000 #
b001 ;
1C
#398
0C
#399
b01110000 #
b000 ;
1C
1s
#400
0C
b1000 [
1k
#401
b00001000 #
b0010 +
b00000000 3
b100 ;
1C
b00000000 c
0s
#402
0C
0k
#403
b00010000 #
b0001 +
b011 ;
1C
#404
0C
#405
b00100000 #
b0000 +
b00010000 3
b010 ;
1C
b00010000 c
#406
0C
#407
b01000000 #
b001 ;
1C
#408
0C
#409
b10000000 #
b000 ;
1C
1s
#410
0C
b1001 [
1k
#411
b00001001 #
b0010 +
b00000000 3
b100 ;
1C
b00000000 c
0s
#412
0C
0k
#413
b00010010 #
b0001 +
b011 ;
1C
#414
0C
#415
b00100100 #
b0000 +
b00010010 3
b010 ;
1C
b00010010 c
#416
0C
#417
b01001000 #
b001 ;
1C
#418
0C
#419
b10010000 #
b000 ;
1C
1s
#420
0C
b1010 [
1k
#421
b00001010 #
b0010 +
b00000000 3
b100 ;
1C
b00000000 c
0s
#422
0C
0k
#423
b00010100 #
b0001 +
b011 ;
1C
#424
0C
#425
b00101000 #
b0000 +
b00010100 3
b010 ;
1C
b00010100 c
#426
0C
#427
b01010000 #
b001 ;
1C
#428
0C
#429
b10100000 #
b000 ;
1C
1s
#430
0C
b1011 [
1k
#431
b00001011 #
b0010 +
b00000000 3
b100 ;
1C
b00000000 c
0s
#432
0C
0k
#433
b00010110 #
b0001 +
b011 ;
1C
#434
0C
#435
b00101100 #
b0000 +
b00010110 3
b010 ;
1C
b00010110 c
#436
0C
#437
b01011000 #
b001 ;
1C
#438
0C
#439
b10110000 #
b000 ;
1C
1s
#440
0C
b1100 [
1k
#441
b00001100 #
b0010 +
b00000000 3
b100 ;
1C
b00000000 c
0s
#442
0C
0k
#443
b00011000 #
b0001 +
b011 ;
1C
#444
0C
#445
b00110000 #
b0000 +
b00011000 3
b010 ;
1C
b00011000 c
#446
0C
#447
b01100000 #
b001 ;
1C
#448
0C
#449
b11000000 #
b000 ;
1C
1s
#450
0C
b1101 [
1k
#451
b00001101 #
b0010 +
b00000000 3
b100 ;
1C
b00000000 c
0s
#452
0C
0k
#453
b00011010 #
b0001 +
b011 ;
1C
#454
0C
#455
b00110100 #
b0000 +
b00011010 3
b010 ;
1C
b00011010 c
#456
0C
#457
b01101000 #
b001 ;
1C
#458
0C
#459
b11010000 #
b000 ;
1C
1s
#460
0C
b1110 [
1k
#461
b00001110 #
b0010 +
b00000000 3
b100 ;
1C
b00000000 c
0s
#462
0C
0k
#463
b00011100 #
b0001 +
b011 ;
1C
#464
0C
#465
b00111000 #
b0000 +
b00011100 3
b010 ;
1C
b00011100 c
#466
0C
#467
b01110000 #
b001 ;
1C
#468
0C
#469
b11100000 #
b000 ;
1C
1s
#470
0C
b1111 [
1k
#471
b00001111 #
b0010 +
b00000000 3
b100 ;
1C
b00000000 c
0s
#472
0C
0k
#473
b00011110 #
b0001 +
b011 ;
1C
#474
0C
#475
b00111100 #
b0000 +
b00011110 3
b010 ;
1C
b00011110 c
#476
0C
#477
b01111000 #
b001 ;
1C
#478
0C
#479
b11110000 #
b000 ;
1C
1s
#480
0C
b0011 S
b0000 [
1k
#481
b00000000 #
b0011 +
b00000000 3
b100 ;
1C
b00000000 c
0s
#482
0C
0k
#483
b0001 +
b011 ;
1C
#484
0C
#485
b0000 +
b010 ;
1C
#486
0C
#487
b001 ;
1C
#488
0C
#489
b000 ;
1C
1s
#490
0C
b0001 [
1k
#491
b00000001 #
b0011 +
b100 ;
1C
0s
#492
0C
0k
#493
b00000010 #
b0001 +
b00000001 3
b011 ;
1C
b00000001 c
#494
0C
#495
b00000100 #
b0000 +
b00000011 3
b010 ;
1C
b00000011 c
#496
0C
#497
b00001000 #
b001 ;
1C
#498
0C
#499
b00010000 #
b000 ;
1C
1s
#500
0C
b0010 [
1k
#501
b00000010 #
b0011 +
b00000000 3
b100 ;
1C
b00000000 c
0s
#502
0C
0k
#503
b00000100 #
b0001 +
b00000010 3
b011 ;
1C
b00000010 c
#504
0C
#505
b00001000 #
b0000 +
b00000110 3
b010 ;
1C
b00000110 c
#506
0C
#507
b00010000 #
b001 ;
1C
#508
0C
#509
b00100000 #
b000 ;
1C
1s
#510
0C
b0011 [
1k
#511
b00000011 #
b0011 +
b00000000 3
b100 ;
1C
b00000000 c
0s
#512
0C
0k
#513
b00000110 #
b0001 +
b00000011 3
b011 ;
1C
b00000011 c
#514
0C
#515
b00001100 #
b0000 +
b00001001 3
b010 ;
1C
b00001001 c
#516
0C
#517
b00011000 #
b001 ;
1C
#518
0C
#519
b00110000 #
b000 ;
1C
1s
#520
0C
b0100 [
1k
#521
b00000100 #
b0011 +
b00000000 3
b100 ;
1C
b00000000 c
0s
#522
0C
0k
#523
b00001000 #
b0001 +
b00000100 3
b011 ;
1C
b00000100 c
#524
0C
#525
b00010000 #
b0000 +
b00001100 3
b010 ;
1C
b00001100 c
#526
0C
#527
b00100000 #
b001 ;
1C
#528
0C
#529
b01000000 #
b000 ;
1C
1s
#530
0C
b0101 [
1k
#531
b00000101 #
b0011 +
b00000000 3
b100 ;
1C
b00000000 c
0s
#532
0C
0k
#533
b00001010 #
b0001 +
b00000101 3
b011 ;
1C
b00000101 c
#534
0C
#535
b00010100 #
b0000 +
b00001111 3
b010 ;
1C
b00001111 c
#536
0C
#537
b00101000 #
b001 ;
1C
#538
0C
#539
b01010000 #
b000 ;
1C
1s
#540
0C
b0110 [
1k
#541
b00000110 #
b0011 +
b00000000 3
b100 ;
1C
b00000000 c
0s
#542
0C
0k
#543
b00001100 #
b0001 +
b00000110 3
b011 ;
1C
b00000110 c
#544
0C
#545
b00011000 #
b0000 +
b00010010 3
b010 ;
1C
b00010010 c
#546
0C
#547
b00110000 #
b001 ;
1C
#548
0C
#549
b01100000 #
b000 ;
1C
1s
#550
0C
b0111 [
1k
#551
b00000111 #
b0011 +
b00000000 3
b100 ;
1C
b00000000 c
0s
#552
0C
0k
#553
b00001110 #
b0001 +
b00000111 3
b011 ;
1C
b00000111 c
#554
0C
#555
b00011100 #
b0000 +
b00010101 3
b010 ;
1C
b00010101 c
#556
0C
#557
b00111000 #
b001 ;
1C
#558
0C
#559
b01110000 #
b000 ;
1C
1s
#560
0C
b1000 [
1k
#561
b00001000 #
b0011 +
b00000000 3
b100 ;
1C
b00000000 c
0s
#562
0C
0k
#563
b00010000 #
b0001 +
b00001000 3
b011 ;
1C
b00001000 c
#564
0C
#565
b00100000 #
b0000 +
b00011000 3
b010 ;
1C
b00011000 c
#566
0C
#567
b01000000 #
b001 ;
1C
#568
0C
#569
b10000000 #
b000 ;
1C
1s
#570
0C
b1001 [
1k
#571
b00001001 #
b0011 +
b00000000 3
b100 ;
1C
b00000000 c
0s
#572
0C
0k
#573
b00010010 #
b0001 +
b00001001 3
b011 ;
1C
b00001001 c
#574
0C
#575
b00100100 #
b0000 +
b00011011 3
b010 ;
1C
b00011011 c
#576
0C
#577
b01001000 #
b001 ;
1C
#578
0C
#579
b10010000 #
b000 ;
1C
1s
#580
0C
b1010 [
1k
#581
b00001010 #
b0011 +
b00000000 3
b100 ;
1C
b00000000 c
0s
#582
0C
0k
#583
b00010100 #
b0001 +
b00001010 3
b011 ;
1C
b00001010 c
#584
0C
#585
b00101000 #
b0000 +
b00011110 3
b010 ;
1C
b00011110 c
#586
0C
#587
b01010000 #
b001 ;
1C
#588
0C
#589
b10100000 #
b000 ;
1C
1s
#590
0C
b1011 [
1k
#591
b00001011 #
b0011 +
b00000000 3
b100 ;
1C
b00000000 c
0s
#592
0C
0k
#593
b00010110 #
b0001 +
b00001011 3
b011 ;
1C
b00001011 c
#594
0C
#595
b00101100 #
b0000 +
b00100001 3
b010 ;
1C
b00100001 c
#596
0C
#597
b01011000 #
b001 ;
1C
#598
0C
#599
b10110000 #
b000 ;
1C
1s
#600
0C
b1100 [
1k
#601
b00001100 #
b0011 +
b00000000 3
b100 ;
1C
b00000000 c
0s
#602
0C
0k
#603
b00011000 #
b0001 +
b00001100 3
b011 ;
1C
b00001100 c
#604
0C
#605
b00110000 #
b0000 +
b00100100 3
b010 ;
1C
b00100100 c
#606
0C
#607
b01100000 #
b001 ;
1C
#608
0C
#609
b11000000 #
b000 ;
1C
1s
#610
0C
b1101 [
1k
#611
b00001101 #
b0011 +
b00000000 3
b100 ;
1C
b00000000 c
0s
#612
0C
0k
#613
b00011010 #
b0001 +
b00001101 3
b011 ;
1C
b00001101 c
#614
0C
#615
b00110100 #
b0000 +
b00100111 3
b010 ;
1C
b00100111 c
#616
0C
#617
b01101000 #
b001 ;
1C
#618
0C
#619
b11010000 #
b000 ;
1C
1s
#620
0C
b1110 [
1k
#621
b00001110 #
b0011 +
b00000000 3
b100 ;
1C
b00000000 c
0s
#622
0C
0k
#623
b00011100 #
b0001 +
b00001110 3
b011 ;
1C
b00001110 c
#624
0C
#625
b00111000 #
b0000 +
b00101010 3
b010 ;
1C
b00101010 c
#626
0C
#627
b01110000 #
b001 ;
1C
#628
0C
#629
b11100000 #
b000 ;
1C
1s
#630
0C
b1111 [
1k
#631
b00001111 #
b0011 +
b00000000 3
b100 ;
1C
b00000000 c
0s
#632
0C
0k
#633
b00011110 #
b0001 +
b00001111 3
b011 ;
1C
b00001111 c
#634
0C
#635
b00111100 #
b0000 +
b00101101 3
b010 ;
1C
b00101101 c
#636
0C
#637
b01111000 #
b001 ;
1C
#638
0C
#639
b11110000 #
b000 ;
1C
1s
#640
0C
b0100 S
b0000 [
1k
#641
b00000000 #
b0100 +
b00000000 3
b100 ;
1C
b00000000 c
0s
#642
0C
0k
#643
b0010 +
b011 ;
1C
#644
0C
#645
b0001 +
b010 ;
1C
#646
0C
#647
b0000 +
b001 ;
1C
#648
0C
#649
b000 ;
1C
1s
#650
0C
b0001 [
1k
#651
b00000001 #
b0100 +
b100 ;
1C
0s
#652
0C
0k
#653
b00000010 #
b0010 +
b011 ;
1C
#654
0C
#655
b00000100 #
b0001 +
b010 ;
1C
#656
0C
#657
b00001000 #
b0000 +
b00000100 3
b001 ;
1C
b00000100 c
#658
0C
#659
b00010000 #
b000 ;
1C
1s
#660
0C
b0010 [
1k
#661
b00000010 #
b0100 +
b00000000 3
b100 ;
1C
b00000000 c
0s
#662
0C
0k
#663
b00000100 #
b0010 +
b011 ;
1C
#664
0C
#665
b00001000 #
b0001 +
b010 ;
1C
#666
0C
#667
b00010000 #
b0000 +
b00001000 3
b001 ;
1C
b00001000 c
#668
0C
#669
b00100000 #
b000 ;
1C
1s
#670
0C
b0011 [
1k
#671
b00000011 #
b0100 +
b00000000 3
b100 ;
1C
b00000000 c
0s
#672
0C
0k
#673
b00000110 #
b0010 +
b011 ;
1C
#674
0C
#675
b00001100 #
b0001 +
b010 ;
1C
#676
0C
#677
b00011000 #
b0000 +
b00001100 3
b001 ;
1C
b00001100 c
#678
0C
#679
b00110000 #
b000 ;
1C
1s
#680
0C
b0100 [
1k
#681
b00000100 #
b0100 +
b00000000 3
b100 ;
1C
b00000000 c
0s
#682
0C
0k
#683
b00001000 #
b0010 +
b011 ;
1C
#684
0C
#685
b00010000 #
b0001 +
b010 ;
1C
#686
0C
